{"dependencies":[{"name":"/Users/keshiamukenge/Documents/projets/starter-project/package.json","includedInParent":true,"mtime":1652463796605},{"name":"./class/SayHi","loc":{"line":1,"column":18},"parent":"/Users/keshiamukenge/Documents/projets/starter-project/src/App.js","resolved":"/Users/keshiamukenge/Documents/projets/starter-project/src/class/SayHi.js"}],"generated":{"js":"\"use strict\";\n\nvar _SayHi = require(\"./class/SayHi\");\n\nvar _SayHi2 = _interopRequireDefault(_SayHi);\n\nfunction _interopRequireDefault(obj) { return obj && obj.__esModule ? obj : { default: obj }; }\n\nvar name = 'Keshia';\nvar example = new _SayHi2.default(name);","map":{"mappings":[{"generated":{"line":3,"column":0},"source":"App.js","original":{"line":1,"column":0}},{"generated":{"line":9,"column":0},"source":"App.js","original":{"line":3,"column":0}},{"name":"name","generated":{"line":9,"column":4},"source":"App.js","original":{"line":3,"column":6}},{"generated":{"line":9,"column":11},"source":"App.js","original":{"line":3,"column":13}},{"generated":{"line":9,"column":19},"source":"App.js","original":{"line":3,"column":0}},{"generated":{"line":10,"column":0},"source":"App.js","original":{"line":4,"column":0}},{"name":"example","generated":{"line":10,"column":4},"source":"App.js","original":{"line":4,"column":6}},{"generated":{"line":10,"column":14},"source":"App.js","original":{"line":4,"column":16}},{"name":"SayHi","generated":{"line":10,"column":18},"source":"App.js","original":{"line":4,"column":20}},{"generated":{"line":10,"column":33},"source":"App.js","original":{"line":4,"column":16}},{"name":"name","generated":{"line":10,"column":34},"source":"App.js","original":{"line":4,"column":26}},{"generated":{"line":10,"column":38},"source":"App.js","original":{"line":4,"column":16}},{"generated":{"line":10,"column":39},"source":"App.js","original":{"line":4,"column":0}}],"sources":{"App.js":"import SayHi from \"./class/SayHi\";\n\nconst name = 'Keshia';\nconst example = new SayHi(name);"},"lineCount":null}},"hash":"7d4b15e3f6add99a5f1cba70edf473ee","cacheData":{"env":{}},"id":26}